mcp_atlassian/__init__.py
mcp_atlassian/exceptions.py
mcp_atlassian/local_storage.py
mcp_atlassian/confluence/__init__.py
mcp_atlassian/confluence/client.py
mcp_atlassian/confluence/comments.py
mcp_atlassian/confluence/config.py
mcp_atlassian/confluence/constants.py
mcp_atlassian/confluence/labels.py
mcp_atlassian/confluence/pages.py
mcp_atlassian/confluence/search.py
mcp_atlassian/confluence/spaces.py
mcp_atlassian/confluence/users.py
mcp_atlassian/confluence/utils.py
mcp_atlassian/models/__init__.py
mcp_atlassian/models/base.py
mcp_atlassian/models/constants.py
mcp_atlassian/models/confluence/__init__.py
mcp_atlassian/models/confluence/comment.py
mcp_atlassian/models/confluence/common.py
mcp_atlassian/models/confluence/label.py
mcp_atlassian/models/confluence/page.py
mcp_atlassian/models/confluence/search.py
mcp_atlassian/models/confluence/space.py
mcp_atlassian/models/confluence/user_search.py
mcp_atlassian/preprocessing/__init__.py
mcp_atlassian/preprocessing/base.py
mcp_atlassian/preprocessing/confluence.py
mcp_atlassian/servers/__init__.py
mcp_atlassian/servers/context.py
mcp_atlassian/servers/dependencies.py
mcp_atlassian/servers/main.py
mcp_atlassian/servers/confluence/__init__.py
mcp_atlassian/servers/confluence/_server.py
mcp_atlassian/servers/confluence/attachments.py
mcp_atlassian/servers/confluence/comments.py
mcp_atlassian/servers/confluence/pages.py
mcp_atlassian/servers/confluence/spaces.py
mcp_atlassian/servers/confluence/sync.py
mcp_atlassian/utils/__init__.py
mcp_atlassian/utils/date.py
mcp_atlassian/utils/decorators.py
mcp_atlassian/utils/env.py
mcp_atlassian/utils/environment.py
mcp_atlassian/utils/io.py
mcp_atlassian/utils/lifecycle.py
mcp_atlassian/utils/logging.py
mcp_atlassian/utils/request_logging.py
mcp_atlassian/utils/ssl.py
mcp_atlassian/utils/tools.py
mcp_atlassian/utils/urls.py
better_confluence_mcp-0.1.23.dist-info/METADATA
better_confluence_mcp-0.1.23.dist-info/WHEEL
better_confluence_mcp-0.1.23.dist-info/entry_points.txt
better_confluence_mcp-0.1.23.dist-info/licenses/LICENSE
better_confluence_mcp-0.1.23.dist-info/RECORD
