Metadata-Version: 2.4
Name: better-confluence-mcp
Version: 0.1.23
Summary: MCP server for Confluence with local filesystem caching. Sync spaces locally, edit HTML files, and push changes back. Features: tree-based storage, incremental sync, version conflict detection, auto full-sync every 3 days.
Project-URL: Homepage, https://github.com/twinity1/better-confluence-mcp
Project-URL: Repository, https://github.com/twinity1/better-confluence-mcp
Project-URL: Issues, https://github.com/twinity1/better-confluence-mcp/issues
Author-email: Ales Kutek <ales.kutek@designeo.cz>
License: MIT
License-File: LICENSE
Keywords: ai,atlassian,cache,confluence,llm,mcp,sync
Classifier: Development Status :: 4 - Beta
Classifier: Intended Audience :: Developers
Classifier: License :: OSI Approved :: MIT License
Classifier: Programming Language :: Python :: 3
Classifier: Programming Language :: Python :: 3.10
Classifier: Programming Language :: Python :: 3.11
Classifier: Programming Language :: Python :: 3.12
Requires-Python: >=3.10
Requires-Dist: atlassian-python-api>=4.0.0
Requires-Dist: beautifulsoup4>=4.12.3
Requires-Dist: cachetools>=5.0.0
Requires-Dist: click>=8.1.7
Requires-Dist: fastmcp<2.4.0,>=2.3.4
Requires-Dist: httpx>=0.28.0
Requires-Dist: keyring>=25.6.0
Requires-Dist: markdown-to-confluence<0.4.0,>=0.3.0
Requires-Dist: markdown>=3.7.0
Requires-Dist: markdownify>=0.11.6
Requires-Dist: mcp<2.0.0,>=1.8.0
Requires-Dist: mermaid-cli>=0.1.0
Requires-Dist: pydantic<2.12.0,>=2.10.6
Requires-Dist: python-dateutil>=2.9.0.post0
Requires-Dist: python-dotenv>=1.0.1
Requires-Dist: requests[socks]>=2.31.0
Requires-Dist: starlette>=0.37.1
Requires-Dist: thefuzz>=0.22.1
Requires-Dist: trio>=0.29.0
Requires-Dist: types-cachetools>=5.5.0.20240820
Requires-Dist: types-python-dateutil>=2.9.0.20241206
Requires-Dist: uvicorn>=0.27.1
